mastercard_installments_non_fi-0.0.4.dist-info/DESCRIPTION.rst
mastercard_installments_non_fi-0.0.4.dist-info/METADATA
mastercard_installments_non_fi-0.0.4.dist-info/RECORD
mastercard_installments_non_fi-0.0.4.dist-info/WHEEL
mastercard_installments_non_fi-0.0.4.dist-info/metadata.json
mastercard_installments_non_fi-0.0.4.dist-info/top_level.txt
mastercardinstallmentsnonfi/__init__.py
mastercardinstallmentsnonfi/eligibilityandcalculator.py
mastercardinstallmentsnonfi/eligibilityandinstallmentplan.py
mastercardinstallmentsnonfi/resourceconfig.py
